zack_liu_package4/__init__.py
zack_liu_package4/adminsite.py
zack_liu_package4-1.1.1.dist-info/LICENSE
zack_liu_package4-1.1.1.dist-info/METADATA
zack_liu_package4-1.1.1.dist-info/WHEEL
zack_liu_package4-1.1.1.dist-info/top_level.txt
zack_liu_package4-1.1.1.dist-info/RECORD
