Metadata-Version: 2.1
Name: zack_liu_package4
Version: 1.1.1
Summary: zack_liu_package4
Home-page: https://github.com/liuzhimin2019/soho-ui.git
Author: zack_liu
Author-email: liu.zhimin.2019@gmail.com
Classifier: Programming Language :: Python :: 3
Classifier: License :: OSI Approved :: MIT License
Classifier: Operating System :: OS Independent
Requires-Python: >=3
License-File: LICENSE
